[
    {
        "forename": "ARTAK",
        "date_of_birth": "1980/09/10",
        "entity_id": "2013/61292",
        "nationalities": [
            "AM"
        ],
        "name": "ULIKHANYAN",
        "_links": {
            "self": {
                "href": "https://ws-public.interpol.int/notices/v1/red/2013-61292"
            },
            "images": {
                "href": "https://ws-public.interpol.int/notices/v1/red/2013-61292/images"
            }
        }
    },
    {
        "forename": "ARMEN",
        "date_of_birth": "1977/09/06",
        "entity_id": "2011/43971",
        "nationalities": [
            "AM"
        ],
        "name": "SANAMYAN",
        "_links": {
            "self": {
                "href": "https://ws-public.interpol.int/notices/v1/red/2011-43971"
            },
            "images": {
                "href": "https://ws-public.interpol.int/notices/v1/red/2011-43971/images"
            }
        }
    },
    {
        "forename": "VARDAN",
        "date_of_birth": "1984/12/12",
        "entity_id": "2016/67094",
        "nationalities": [
            "AM"
        ],
        "name": "PIRUZYAN",
        "_links": {
            "self": {
                "href": "https://ws-public.interpol.int/notices/v1/red/2016-67094"
            },
            "images": {
                "href": "https://ws-public.interpol.int/notices/v1/red/2016-67094/images"
            },
            "thumbnail": {
                "href": "https://ws-public.interpol.int/notices/v1/red/2016-67094/images/60206924"
            }
        }
    },
    {
        "forename": "VITALI",
        "date_of_birth": "1979/05/16",
        "entity_id": "2010/50783",
        "nationalities": [
            "AM"
        ],
        "name": "AMIRKHANYAN",
        "_links": {
            "self": {
                "href": "https://ws-public.interpol.int/notices/v1/red/2010-50783"
            },
            "images": {
                "href": "https://ws-public.interpol.int/notices/v1/red/2010-50783/images"
            }
        }
    },
    {
        "forename": "LEVON",
        "date_of_birth": "1977/07/18",
        "entity_id": "2016/21870",
        "nationalities": [
            "AM"
        ],
        "name": "SAAKYAN",
        "_links": {
            "self": {
                "href": "https://ws-public.interpol.int/notices/v1/red/2016-21870"
            },
            "images": {
                "href": "https://ws-public.interpol.int/notices/v1/red/2016-21870/images"
            }
        }
    },
    {
        "forename": "HAYK",
        "date_of_birth": "1988/01/07",
        "entity_id": "2016/16056",
        "nationalities": [
            "AM"
        ],
        "name": "TERTERIAN",
        "_links": {
            "self": {
                "href": "https://ws-public.interpol.int/notices/v1/red/2016-16056"
            },
            "images": {
                "href": "https://ws-public.interpol.int/notices/v1/red/2016-16056/images"
            },
            "thumbnail": {
                "href": "https://ws-public.interpol.int/notices/v1/red/2016-16056/images/60032148"
            }
        }
    },
    {
        "forename": "NORIK",
        "date_of_birth": "1978/11/20",
        "entity_id": "2011/69048",
        "nationalities": [
            "AM"
        ],
        "name": "ZARGARYAN",
        "_links": {
            "self": {
                "href": "https://ws-public.interpol.int/notices/v1/red/2011-69048"
            },
            "images": {
                "href": "https://ws-public.interpol.int/notices/v1/red/2011-69048/images"
            }
        }
    },
    {
        "forename": "ARUTYUN",
        "date_of_birth": "1979/02/25",
        "entity_id": "2015/43692",
        "nationalities": [
            "AM",
            "RU"
        ],
        "name": "MEYROYAN",
        "_links": {
            "self": {
                "href": "https://ws-public.interpol.int/notices/v1/red/2015-43692"
            },
            "images": {
                "href": "https://ws-public.interpol.int/notices/v1/red/2015-43692/images"
            },
            "thumbnail": {
                "href": "https://ws-public.interpol.int/notices/v1/red/2015-43692/images/59835225"
            }
        }
    },
    {
        "forename": "SARGIS",
        "date_of_birth": "1978/08/04",
        "entity_id": "2015/33441",
        "nationalities": [
            "AM"
        ],
        "name": "MAKARYAN",
        "_links": {
            "self": {
                "href": "https://ws-public.interpol.int/notices/v1/red/2015-33441"
            },
            "images": {
                "href": "https://ws-public.interpol.int/notices/v1/red/2015-33441/images"
            }
        }
    },
    {
        "forename": "MIHRAN",
        "date_of_birth": "1956/12/22",
        "entity_id": "2010/34000",
        "nationalities": [
            "RU",
            "AM"
        ],
        "name": "CHAGHARYAN",
        "_links": {
            "self": {
                "href": "https://ws-public.interpol.int/notices/v1/red/2010-34000"
            },
            "images": {
                "href": "https://ws-public.interpol.int/notices/v1/red/2010-34000/images"
            },
            "thumbnail": {
                "href": "https://ws-public.interpol.int/notices/v1/red/2010-34000/images/59687950"
            }
        }
    },
    {
        "forename": "ARAYIK",
        "date_of_birth": "1973/07/14",
        "entity_id": "2014/64315",
        "nationalities": [
            "RU",
            "AM"
        ],
        "name": "ENGIBARYAN",
        "_links": {
            "self": {
                "href": "https://ws-public.interpol.int/notices/v1/red/2014-64315"
            },
            "images": {
                "href": "https://ws-public.interpol.int/notices/v1/red/2014-64315/images"
            },
            "thumbnail": {
                "href": "https://ws-public.interpol.int/notices/v1/red/2014-64315/images/59637903"
            }
        }
    },
    {
        "forename": "ARMENUHI",
        "date_of_birth": "1987/05/24",
        "entity_id": "2014/2935",
        "nationalities": [
            "AM"
        ],
        "name": "PETROSYAN",
        "_links": {
            "self": {
                "href": "https://ws-public.interpol.int/notices/v1/red/2014-2935"
            },
            "images": {
                "href": "https://ws-public.interpol.int/notices/v1/red/2014-2935/images"
            },
            "thumbnail": {
                "href": "https://ws-public.interpol.int/notices/v1/red/2014-2935/images/59399060"
            }
        }
    },
    {
        "forename": "DAVID",
        "date_of_birth": "1983/05/09",
        "entity_id": "2013/72116",
        "nationalities": [
            "AM"
        ],
        "name": "CHITCHYAN",
        "_links": {
            "self": {
                "href": "https://ws-public.interpol.int/notices/v1/red/2013-72116"
            },
            "images": {
                "href": "https://ws-public.interpol.int/notices/v1/red/2013-72116/images"
            },
            "thumbnail": {
                "href": "https://ws-public.interpol.int/notices/v1/red/2013-72116/images/59383549"
            }
        }
    },
    {
        "forename": "ARSEN",
        "date_of_birth": "1977/02/28",
        "entity_id": "2012/327619",
        "nationalities": [
            "AM"
        ],
        "name": "DANIELYAN",
        "_links": {
            "self": {
                "href": "https://ws-public.interpol.int/notices/v1/red/2012-327619"
            },
            "images": {
                "href": "https://ws-public.interpol.int/notices/v1/red/2012-327619/images"
            }
        }
    },
    {
        "forename": "LAVRENTIY",
        "date_of_birth": "1985/10/30",
        "entity_id": "2012/313364",
        "nationalities": [
            "AM"
        ],
        "name": "SHAVINYAN",
        "_links": {
            "self": {
                "href": "https://ws-public.interpol.int/notices/v1/red/2012-313364"
            },
            "images": {
                "href": "https://ws-public.interpol.int/notices/v1/red/2012-313364/images"
            },
            "thumbnail": {
                "href": "https://ws-public.interpol.int/notices/v1/red/2012-313364/images/57100056"
            }
        }
    },
    {
        "forename": "SARKIS",
        "date_of_birth": "1986/03/14",
        "entity_id": "2011/23500",
        "nationalities": [
            "AM",
            "US"
        ],
        "name": "AMBARTSUMYAN",
        "_links": {
            "self": {
                "href": "https://ws-public.interpol.int/notices/v1/red/2011-23500"
            },
            "images": {
                "href": "https://ws-public.interpol.int/notices/v1/red/2011-23500/images"
            },
            "thumbnail": {
                "href": "https://ws-public.interpol.int/notices/v1/red/2011-23500/images/55275900"
            }
        }
    },
    {
        "forename": "KAREN",
        "date_of_birth": "1966/09/04",
        "entity_id": "2010/24533",
        "nationalities": [
            "AM"
        ],
        "name": "GEVORGYAN",
        "_links": {
            "self": {
                "href": "https://ws-public.interpol.int/notices/v1/red/2010-24533"
            },
            "images": {
                "href": "https://ws-public.interpol.int/notices/v1/red/2010-24533/images"
            },
            "thumbnail": {
                "href": "https://ws-public.interpol.int/notices/v1/red/2010-24533/images/54405469"
            }
        }
    },
    {
        "forename": "ARMEN",
        "date_of_birth": "1964/10/03",
        "entity_id": "2010/22073",
        "nationalities": [
            "AM"
        ],
        "name": "OGANESJAN",
        "_links": {
            "self": {
                "href": "https://ws-public.interpol.int/notices/v1/red/2010-22073"
            },
            "images": {
                "href": "https://ws-public.interpol.int/notices/v1/red/2010-22073/images"
            },
            "thumbnail": {
                "href": "https://ws-public.interpol.int/notices/v1/red/2010-22073/images/54391957"
            }
        }
    },
    {
        "forename": "ARMEN",
        "date_of_birth": "1958/11/16",
        "entity_id": "2009/39054",
        "nationalities": [
            "AM"
        ],
        "name": "KALANTARYAN",
        "_links": {
            "self": {
                "href": "https://ws-public.interpol.int/notices/v1/red/2009-39054"
            },
            "images": {
                "href": "https://ws-public.interpol.int/notices/v1/red/2009-39054/images"
            },
            "thumbnail": {
                "href": "https://ws-public.interpol.int/notices/v1/red/2009-39054/images/54259353"
            }
        }
    },
    {
        "forename": "GRISHA",
        "date_of_birth": "1964/09/05",
        "entity_id": "2005/19818",
        "nationalities": [
            "AM"
        ],
        "name": "ALEKSANYAN",
        "_links": {
            "self": {
                "href": "https://ws-public.interpol.int/notices/v1/red/2005-19818"
            },
            "images": {
                "href": "https://ws-public.interpol.int/notices/v1/red/2005-19818/images"
            },
            "thumbnail": {
                "href": "https://ws-public.interpol.int/notices/v1/red/2005-19818/images/61239634"
            }
        }
    },
    {
        "forename": "SERGO",
        "date_of_birth": "1970/01/01",
        "entity_id": "2003/2619",
        "nationalities": [
            "AM"
        ],
        "name": "SARGSYAN",
        "_links": {
            "self": {
                "href": "https://ws-public.interpol.int/notices/v1/red/2003-2619"
            },
            "images": {
                "href": "https://ws-public.interpol.int/notices/v1/red/2003-2619/images"
            },
            "thumbnail": {
                "href": "https://ws-public.interpol.int/notices/v1/red/2003-2619/images/61428358"
            }
        }
    },
    {
        "forename": "ARAKEL",
        "date_of_birth": "1965/02/07",
        "entity_id": "2003/30788",
        "nationalities": [
            "AM"
        ],
        "name": "SARGSYAN",
        "_links": {
            "self": {
                "href": "https://ws-public.interpol.int/notices/v1/red/2003-30788"
            },
            "images": {
                "href": "https://ws-public.interpol.int/notices/v1/red/2003-30788/images"
            },
            "thumbnail": {
                "href": "https://ws-public.interpol.int/notices/v1/red/2003-30788/images/60977765"
            }
        }
    },
    {
        "forename": "ARTUR",
        "date_of_birth": "1966/07/12",
        "entity_id": "2003/12756",
        "nationalities": [
            "AM"
        ],
        "name": "GYULNAZARYAN",
        "_links": {
            "self": {
                "href": "https://ws-public.interpol.int/notices/v1/red/2003-12756"
            },
            "images": {
                "href": "https://ws-public.interpol.int/notices/v1/red/2003-12756/images"
            },
            "thumbnail": {
                "href": "https://ws-public.interpol.int/notices/v1/red/2003-12756/images/60976645"
            }
        }
    },
    {
        "forename": "VANO",
        "date_of_birth": "1946/11/13",
        "entity_id": "2000/17015",
        "nationalities": [
            "AM"
        ],
        "name": "SIRADEGHYAN",
        "_links": {
            "self": {
                "href": "https://ws-public.interpol.int/notices/v1/red/2000-17015"
            },
            "images": {
                "href": "https://ws-public.interpol.int/notices/v1/red/2000-17015/images"
            },
            "thumbnail": {
                "href": "https://ws-public.interpol.int/notices/v1/red/2000-17015/images/52420762"
            }
        }
    }
]