[
    {
        "forename": "DRAGAN",
        "date_of_birth": "1987/02/09",
        "entity_id": "2014/75744",
        "nationalities": [
            "ME"
        ],
        "name": "GAJIC",
        "_links": {
            "self": {
                "href": "https://ws-public.interpol.int/notices/v1/red/2014-75744"
            },
            "images": {
                "href": "https://ws-public.interpol.int/notices/v1/red/2014-75744/images"
            },
            "thumbnail": {
                "href": "https://ws-public.interpol.int/notices/v1/red/2014-75744/images/59675705"
            }
        }
    },
    {
        "forename": "ALEN",
        "date_of_birth": "1984/05/28",
        "entity_id": "2014/50316",
        "nationalities": [
            "ME",
            "SK"
        ],
        "name": "VELOVIC",
        "_links": {
            "self": {
                "href": "https://ws-public.interpol.int/notices/v1/red/2014-50316"
            },
            "images": {
                "href": "https://ws-public.interpol.int/notices/v1/red/2014-50316/images"
            },
            "thumbnail": {
                "href": "https://ws-public.interpol.int/notices/v1/red/2014-50316/images/59587956"
            }
        }
    },
    {
        "forename": "DEJAN",
        "date_of_birth": "1980/05/01",
        "entity_id": "2010/9469",
        "nationalities": [
            "ME"
        ],
        "name": "SEKULARAC",
        "_links": {
            "self": {
                "href": "https://ws-public.interpol.int/notices/v1/red/2010-9469"
            },
            "images": {
                "href": "https://ws-public.interpol.int/notices/v1/red/2010-9469/images"
            }
        }
    },
    {
        "forename": "GORAN",
        "date_of_birth": "1979/03/19",
        "entity_id": "2009/35192",
        "nationalities": [
            "ME"
        ],
        "name": "MILASINOVIC",
        "_links": {
            "self": {
                "href": "https://ws-public.interpol.int/notices/v1/red/2009-35192"
            },
            "images": {
                "href": "https://ws-public.interpol.int/notices/v1/red/2009-35192/images"
            },
            "thumbnail": {
                "href": "https://ws-public.interpol.int/notices/v1/red/2009-35192/images/54418268"
            }
        }
    },
    {
        "forename": "BOZIDAR",
        "date_of_birth": "1979/01/07",
        "entity_id": "2006/36409",
        "nationalities": [
            "ME"
        ],
        "name": "SAMARDZIC",
        "_links": {
            "self": {
                "href": "https://ws-public.interpol.int/notices/v1/red/2006-36409"
            },
            "images": {
                "href": "https://ws-public.interpol.int/notices/v1/red/2006-36409/images"
            },
            "thumbnail": {
                "href": "https://ws-public.interpol.int/notices/v1/red/2006-36409/images/55380810"
            }
        }
    }
]