[
    {
        "forename": "AUNG WIN",
        "date_of_birth": "1972/03/06",
        "entity_id": "2017/130126",
        "nationalities": [
            "MM"
        ],
        "name": "KHINE",
        "_links": {
            "self": {
                "href": "https://ws-public.interpol.int/notices/v1/red/2017-130126"
            },
            "images": {
                "href": "https://ws-public.interpol.int/notices/v1/red/2017-130126/images"
            },
            "thumbnail": {
                "href": "https://ws-public.interpol.int/notices/v1/red/2017-130126/images/60560347"
            }
        }
    },
    {
        "forename": "SHANGWANG SHANGYUNG KHAPLANG",
        "date_of_birth": "1940",
        "entity_id": "2016/54005",
        "nationalities": [
            "MM"
        ],
        "name": "PANGMEI",
        "_links": {
            "self": {
                "href": "https://ws-public.interpol.int/notices/v1/red/2016-54005"
            },
            "images": {
                "href": "https://ws-public.interpol.int/notices/v1/red/2016-54005/images"
            },
            "thumbnail": {
                "href": "https://ws-public.interpol.int/notices/v1/red/2016-54005/images/60160300"
            }
        }
    },
    {
        "forename": "HTET",
        "date_of_birth": "1994/05/26",
        "entity_id": "2015/32885",
        "nationalities": [
            "MM"
        ],
        "name": "PYAE AUNG",
        "_links": {
            "self": {
                "href": "https://ws-public.interpol.int/notices/v1/red/2015-32885"
            },
            "images": {
                "href": "https://ws-public.interpol.int/notices/v1/red/2015-32885/images"
            },
            "thumbnail": {
                "href": "https://ws-public.interpol.int/notices/v1/red/2015-32885/images/59799669"
            }
        }
    },
    {
        "forename": "YE KYAW",
        "date_of_birth": "1980/02/14",
        "entity_id": "2015/21607",
        "nationalities": [
            "MM"
        ],
        "name": "SOE",
        "_links": {
            "self": {
                "href": "https://ws-public.interpol.int/notices/v1/red/2015-21607"
            },
            "images": {
                "href": "https://ws-public.interpol.int/notices/v1/red/2015-21607/images"
            },
            "thumbnail": {
                "href": "https://ws-public.interpol.int/notices/v1/red/2015-21607/images/59759970"
            }
        }
    },
    {
        "forename": "BAIKTHA",
        "date_of_birth": "1961",
        "entity_id": "2004/18141",
        "nationalities": [
            "MM"
        ],
        "name": "BAIKTHA KIMA",
        "_links": {
            "self": {
                "href": "https://ws-public.interpol.int/notices/v1/red/2004-18141"
            },
            "images": {
                "href": "https://ws-public.interpol.int/notices/v1/red/2004-18141/images"
            },
            "thumbnail": {
                "href": "https://ws-public.interpol.int/notices/v1/red/2004-18141/images/61390160"
            }
        }
    }
]