[
    {
        "forename": "KRISTINE JOY DY",
        "date_of_birth": "1986/12/22",
        "entity_id": "2018/59735",
        "nationalities": [
            "PH"
        ],
        "name": "ACTA",
        "_links": {
            "self": {
                "href": "https://ws-public.interpol.int/notices/v1/red/2018-59735"
            },
            "images": {
                "href": "https://ws-public.interpol.int/notices/v1/red/2018-59735/images"
            },
            "thumbnail": {
                "href": "https://ws-public.interpol.int/notices/v1/red/2018-59735/images/61103688"
            }
        }
    },
    {
        "forename": "JASPER ABRINGE",
        "date_of_birth": "1988/10/14",
        "entity_id": "2018/14636",
        "nationalities": [
            "PH"
        ],
        "name": "DELOS ANGELES",
        "_links": {
            "self": {
                "href": "https://ws-public.interpol.int/notices/v1/red/2018-14636"
            },
            "images": {
                "href": "https://ws-public.interpol.int/notices/v1/red/2018-14636/images"
            },
            "thumbnail": {
                "href": "https://ws-public.interpol.int/notices/v1/red/2018-14636/images/60960845"
            }
        }
    },
    {
        "forename": "CHERYL SALDIVAR ARAGO",
        "date_of_birth": "1956/07/28",
        "entity_id": "2018/2936",
        "nationalities": [
            "PH"
        ],
        "name": "CAPILI",
        "_links": {
            "self": {
                "href": "https://ws-public.interpol.int/notices/v1/red/2018-2936"
            },
            "images": {
                "href": "https://ws-public.interpol.int/notices/v1/red/2018-2936/images"
            },
            "thumbnail": {
                "href": "https://ws-public.interpol.int/notices/v1/red/2018-2936/images/60918220"
            }
        }
    },
    {
        "forename": "OSCAR PAUL BIALOGLOVSKI",
        "date_of_birth": "1980/11/30",
        "entity_id": "2017/283438",
        "nationalities": [
            "PH"
        ],
        "name": "VALLE",
        "_links": {
            "self": {
                "href": "https://ws-public.interpol.int/notices/v1/red/2017-283438"
            },
            "images": {
                "href": "https://ws-public.interpol.int/notices/v1/red/2017-283438/images"
            },
            "thumbnail": {
                "href": "https://ws-public.interpol.int/notices/v1/red/2017-283438/images/60876872"
            }
        }
    },
    {
        "forename": "JOHN G.",
        "date_of_birth": "1966/10/20",
        "entity_id": "2017/199266",
        "nationalities": [
            "PH",
            "US"
        ],
        "name": "PANALIGAN",
        "_links": {
            "self": {
                "href": "https://ws-public.interpol.int/notices/v1/red/2017-199266"
            },
            "images": {
                "href": "https://ws-public.interpol.int/notices/v1/red/2017-199266/images"
            },
            "thumbnail": {
                "href": "https://ws-public.interpol.int/notices/v1/red/2017-199266/images/60746314"
            }
        }
    },
    {
        "forename": "ABDULLAH R",
        "date_of_birth": "1983",
        "entity_id": "2017/191848",
        "nationalities": [
            "PH"
        ],
        "name": "MAUTE",
        "_links": {
            "self": {
                "href": "https://ws-public.interpol.int/notices/v1/red/2017-191848"
            },
            "images": {
                "href": "https://ws-public.interpol.int/notices/v1/red/2017-191848/images"
            },
            "thumbnail": {
                "href": "https://ws-public.interpol.int/notices/v1/red/2017-191848/images/60742474"
            }
        }
    },
    {
        "forename": "FURUDJI AMIRIN",
        "date_of_birth": "1980",
        "entity_id": "2016/92275",
        "nationalities": [
            "PH"
        ],
        "name": "INDAMA",
        "_links": {
            "self": {
                "href": "https://ws-public.interpol.int/notices/v1/red/2016-92275"
            },
            "images": {
                "href": "https://ws-public.interpol.int/notices/v1/red/2016-92275/images"
            },
            "thumbnail": {
                "href": "https://ws-public.interpol.int/notices/v1/red/2016-92275/images/61232826"
            }
        }
    },
    {
        "forename": "MOHAMMAD MACA-ANTAL",
        "date_of_birth": "1961/07/12",
        "entity_id": "2017/187590",
        "nationalities": [
            "PH"
        ],
        "name": "SAID",
        "_links": {
            "self": {
                "href": "https://ws-public.interpol.int/notices/v1/red/2017-187590"
            },
            "images": {
                "href": "https://ws-public.interpol.int/notices/v1/red/2017-187590/images"
            },
            "thumbnail": {
                "href": "https://ws-public.interpol.int/notices/v1/red/2017-187590/images/60706979"
            }
        }
    },
    {
        "forename": "ISNILON",
        "date_of_birth": "1966/03/18",
        "entity_id": "2016/92313",
        "nationalities": [
            "PH"
        ],
        "name": "HAPILON",
        "_links": {
            "self": {
                "href": "https://ws-public.interpol.int/notices/v1/red/2016-92313"
            },
            "images": {
                "href": "https://ws-public.interpol.int/notices/v1/red/2016-92313/images"
            }
        }
    },
    {
        "forename": "KHRISTOPHER IAN CASTRO",
        "date_of_birth": "1985/08/02",
        "entity_id": "2017/174198",
        "nationalities": [
            "PH"
        ],
        "name": "RUMBAUA",
        "_links": {
            "self": {
                "href": "https://ws-public.interpol.int/notices/v1/red/2017-174198"
            },
            "images": {
                "href": "https://ws-public.interpol.int/notices/v1/red/2017-174198/images"
            },
            "thumbnail": {
                "href": "https://ws-public.interpol.int/notices/v1/red/2017-174198/images/60678479"
            }
        }
    },
    {
        "forename": "ARTURO BARIQUIT",
        "date_of_birth": "1960/12/16",
        "entity_id": "2017/169689",
        "nationalities": [
            "PH"
        ],
        "name": "LASCA\u00d1AS",
        "_links": {
            "self": {
                "href": "https://ws-public.interpol.int/notices/v1/red/2017-169689"
            },
            "images": {
                "href": "https://ws-public.interpol.int/notices/v1/red/2017-169689/images"
            },
            "thumbnail": {
                "href": "https://ws-public.interpol.int/notices/v1/red/2017-169689/images/60662281"
            }
        }
    },
    {
        "forename": "MARIA KATHRINA KATLEEN MALIGRO",
        "date_of_birth": "1987/09/14",
        "entity_id": "2017/124954",
        "nationalities": [
            "PH"
        ],
        "name": "MOUNTNEY",
        "_links": {
            "self": {
                "href": "https://ws-public.interpol.int/notices/v1/red/2017-124954"
            },
            "images": {
                "href": "https://ws-public.interpol.int/notices/v1/red/2017-124954/images"
            },
            "thumbnail": {
                "href": "https://ws-public.interpol.int/notices/v1/red/2017-124954/images/60545944"
            }
        }
    },
    {
        "forename": "CRISANTO",
        "date_of_birth": "1967/07/29",
        "entity_id": "2016/58605",
        "nationalities": [
            "PH"
        ],
        "name": "PINKIHAN ATTOLBA",
        "_links": {
            "self": {
                "href": "https://ws-public.interpol.int/notices/v1/red/2016-58605"
            },
            "images": {
                "href": "https://ws-public.interpol.int/notices/v1/red/2016-58605/images"
            },
            "thumbnail": {
                "href": "https://ws-public.interpol.int/notices/v1/red/2016-58605/images/60177153"
            }
        }
    },
    {
        "forename": "RENE R.",
        "date_of_birth": "1968/05/24",
        "entity_id": "2012/2988",
        "nationalities": [
            "PH"
        ],
        "name": "VELASCO",
        "_links": {
            "self": {
                "href": "https://ws-public.interpol.int/notices/v1/red/2012-2988"
            },
            "images": {
                "href": "https://ws-public.interpol.int/notices/v1/red/2012-2988/images"
            },
            "thumbnail": {
                "href": "https://ws-public.interpol.int/notices/v1/red/2012-2988/images/56593069"
            }
        }
    },
    {
        "forename": "KINO MICHAEL",
        "date_of_birth": "1952/05/09",
        "entity_id": "2010/3616",
        "nationalities": [
            "US",
            "PH"
        ],
        "name": "GOMEZ",
        "_links": {
            "self": {
                "href": "https://ws-public.interpol.int/notices/v1/red/2010-3616"
            },
            "images": {
                "href": "https://ws-public.interpol.int/notices/v1/red/2010-3616/images"
            },
            "thumbnail": {
                "href": "https://ws-public.interpol.int/notices/v1/red/2010-3616/images/54302446"
            }
        }
    },
    {
        "forename": "EMMANUEL OLILANG",
        "date_of_birth": "1958/10/29",
        "entity_id": "2008/18128",
        "nationalities": [
            "PH"
        ],
        "name": "OMEMAGA",
        "_links": {
            "self": {
                "href": "https://ws-public.interpol.int/notices/v1/red/2008-18128"
            },
            "images": {
                "href": "https://ws-public.interpol.int/notices/v1/red/2008-18128/images"
            },
            "thumbnail": {
                "href": "https://ws-public.interpol.int/notices/v1/red/2008-18128/images/53932219"
            }
        }
    },
    {
        "forename": "ABELARDO MARIANO",
        "date_of_birth": "1946/04/20",
        "entity_id": "2007/22985",
        "nationalities": [
            "PH"
        ],
        "name": "TASA",
        "_links": {
            "self": {
                "href": "https://ws-public.interpol.int/notices/v1/red/2007-22985"
            },
            "images": {
                "href": "https://ws-public.interpol.int/notices/v1/red/2007-22985/images"
            },
            "thumbnail": {
                "href": "https://ws-public.interpol.int/notices/v1/red/2007-22985/images/61238534"
            }
        }
    }
]