[
    {
        "forename": "MARIO ANTONIO",
        "date_of_birth": "1959/08/20",
        "entity_id": "2017/189523",
        "nationalities": [
            "US",
            "PT"
        ],
        "name": "FONSECA",
        "_links": {
            "self": {
                "href": "https://ws-public.interpol.int/notices/v1/red/2017-189523"
            },
            "images": {
                "href": "https://ws-public.interpol.int/notices/v1/red/2017-189523/images"
            },
            "thumbnail": {
                "href": "https://ws-public.interpol.int/notices/v1/red/2017-189523/images/60714380"
            }
        }
    },
    {
        "forename": "SERAFIM",
        "date_of_birth": "1957/09/09",
        "entity_id": "2017/188099",
        "nationalities": [
            "PT"
        ],
        "name": "PEREIRA ALMEIDA DA CRUZ",
        "_links": {
            "self": {
                "href": "https://ws-public.interpol.int/notices/v1/red/2017-188099"
            },
            "images": {
                "href": "https://ws-public.interpol.int/notices/v1/red/2017-188099/images"
            },
            "thumbnail": {
                "href": "https://ws-public.interpol.int/notices/v1/red/2017-188099/images/60709141"
            }
        }
    },
    {
        "forename": "DOMINGOS",
        "date_of_birth": "1955/11/20",
        "entity_id": "2017/13478",
        "nationalities": [
            "PT"
        ],
        "name": "DUARTE LIMA",
        "_links": {
            "self": {
                "href": "https://ws-public.interpol.int/notices/v1/red/2017-13478"
            },
            "images": {
                "href": "https://ws-public.interpol.int/notices/v1/red/2017-13478/images"
            },
            "thumbnail": {
                "href": "https://ws-public.interpol.int/notices/v1/red/2017-13478/images/60321337"
            }
        }
    },
    {
        "forename": "JOAO PAULO",
        "date_of_birth": "1967/01/31",
        "entity_id": "2016/26808",
        "nationalities": [
            "PT"
        ],
        "name": "FERREIRA MARQUES",
        "_links": {
            "self": {
                "href": "https://ws-public.interpol.int/notices/v1/red/2016-26808"
            },
            "images": {
                "href": "https://ws-public.interpol.int/notices/v1/red/2016-26808/images"
            }
        }
    },
    {
        "forename": "CARLOS MIGUEL",
        "date_of_birth": "1970/01/15",
        "entity_id": "2014/56100",
        "nationalities": [
            "PT"
        ],
        "name": "PINA DE CASTRO E SILVA",
        "_links": {
            "self": {
                "href": "https://ws-public.interpol.int/notices/v1/red/2014-56100"
            },
            "images": {
                "href": "https://ws-public.interpol.int/notices/v1/red/2014-56100/images"
            },
            "thumbnail": {
                "href": "https://ws-public.interpol.int/notices/v1/red/2014-56100/images/59609666"
            }
        }
    },
    {
        "forename": "CARLOS",
        "date_of_birth": "1962/02/17",
        "entity_id": "2014/4205",
        "nationalities": [
            "US",
            "PT"
        ],
        "name": "BOLIEIRO",
        "_links": {
            "self": {
                "href": "https://ws-public.interpol.int/notices/v1/red/2014-4205"
            },
            "images": {
                "href": "https://ws-public.interpol.int/notices/v1/red/2014-4205/images"
            },
            "thumbnail": {
                "href": "https://ws-public.interpol.int/notices/v1/red/2014-4205/images/59403691"
            }
        }
    },
    {
        "forename": "JOS\u00c9 ANT\u00d4NIO DE PALINHOS JORGE PEREIRA",
        "date_of_birth": "1950/08/20",
        "entity_id": "2011/9317",
        "nationalities": [
            "PT"
        ],
        "name": "COHEN",
        "_links": {
            "self": {
                "href": "https://ws-public.interpol.int/notices/v1/red/2011-9317"
            },
            "images": {
                "href": "https://ws-public.interpol.int/notices/v1/red/2011-9317/images"
            },
            "thumbnail": {
                "href": "https://ws-public.interpol.int/notices/v1/red/2011-9317/images/55011609"
            }
        }
    },
    {
        "forename": "DANIEL",
        "date_of_birth": "1969/10/29",
        "entity_id": "2010/41507",
        "nationalities": [
            "PT",
            "US"
        ],
        "name": "COSTA",
        "_links": {
            "self": {
                "href": "https://ws-public.interpol.int/notices/v1/red/2010-41507"
            },
            "images": {
                "href": "https://ws-public.interpol.int/notices/v1/red/2010-41507/images"
            },
            "thumbnail": {
                "href": "https://ws-public.interpol.int/notices/v1/red/2010-41507/images/54482801"
            }
        }
    },
    {
        "forename": "JORGE",
        "date_of_birth": "1959/04/19",
        "entity_id": "2007/44920",
        "nationalities": [
            "PT"
        ],
        "name": "MANOEL ROSA MONTEIRO",
        "_links": {
            "self": {
                "href": "https://ws-public.interpol.int/notices/v1/red/2007-44920"
            },
            "images": {
                "href": "https://ws-public.interpol.int/notices/v1/red/2007-44920/images"
            },
            "thumbnail": {
                "href": "https://ws-public.interpol.int/notices/v1/red/2007-44920/images/53778971"
            }
        }
    },
    {
        "forename": "ANTONIO PALINHOS",
        "date_of_birth": "1946/01/01",
        "entity_id": "2007/44907",
        "nationalities": [
            "PT"
        ],
        "name": "JORGE PEREIRA",
        "_links": {
            "self": {
                "href": "https://ws-public.interpol.int/notices/v1/red/2007-44907"
            },
            "images": {
                "href": "https://ws-public.interpol.int/notices/v1/red/2007-44907/images"
            }
        }
    }
]